Metadata-Version: 2.1
Name: Skills-ML
Version: 2.0.0
Summary: Algorithms for Jobs/skills taxonomy creation
Home-page: https://github.com/workforce-data-initiative/skills-ml
Author: Center for Data Science and Public Policy
Author-email: datascifellows@gmail.com
License: MIT license
Keywords: nlp jobs skills onet
Platform: UNKNOWN
Classifier: Development Status :: 2 - Pre-Alpha
Classifier: Intended Audience :: Developers
Classifier: License :: OSI Approved :: MIT License
Classifier: Natural Language :: English
Classifier: Programming Language :: Python :: 3
Classifier: Programming Language :: Python :: 3.6
Requires-Dist: pandas (==0.22.0)
Requires-Dist: requests (==2.18.4)
Requires-Dist: scikit-learn (==0.19.1)
Requires-Dist: scipy (==1.0.1)
Requires-Dist: nltk (==3.2.5)
Requires-Dist: pytest (==3.5.1)
Requires-Dist: PyYAML (==3.12)
Requires-Dist: Elasticsearch (==6.2.0)
Requires-Dist: gensim (==3.2.0)
Requires-Dist: annoy (==1.11.5)
Requires-Dist: unicodecsv (==0.14.1)
Requires-Dist: us (==1.0.0)
Requires-Dist: Sqlalchemy (==1.2.7)
Requires-Dist: geocoder (==1.38.1)
Requires-Dist: psycopg2 (==2.7.4)
Requires-Dist: alembic (==0.9.9)
Requires-Dist: retrying (==1.3.3)
Requires-Dist: fiona (==1.7.11.post1)
Requires-Dist: shapely (==1.6.4.post1)
Requires-Dist: filelock (==3.0.4)
Requires-Dist: bs4 (==0.0.1)
Requires-Dist: lxml (==4.2.1)
Requires-Dist: fuzzywuzzy (==0.16.0)
Requires-Dist: python-Levenshtein (==0.12.0)
Requires-Dist: dickens (==1.0.1)
Requires-Dist: skills-utils (==0.4.0)
